openforms/__init__.py
openforms/forms.py
openforms/lists.py
openforms-0.0.7.dist-info/LICENSE
openforms-0.0.7.dist-info/METADATA
openforms-0.0.7.dist-info/WHEEL
openforms-0.0.7.dist-info/top_level.txt
openforms-0.0.7.dist-info/RECORD
