Metadata-Version: 2.1
Name: openforms
Version: 0.0.7
Summary: Packages for the OpenForms API
Home-page: https://github.com/GRInnovation/openforms
Author: Zac Thiel
Author-email: digitalservices@grcity.us
License: UNKNOWN
Platform: UNKNOWN
Classifier: Programming Language :: Python :: 3
Classifier: License :: OSI Approved :: MIT License
Classifier: Operating System :: OS Independent
Requires-Python: >=3.7
